Metadata-Version: 2.4
Name: pyboot-commons-jwt
Version: 1.3.3
Summary: Pyboot-commons-jwt is an open-source utility package that simplifies the development of jwt.
Author-email: joinsunsoft <793875613@qq.com>
Maintainer-email: joinsunsoft <inthirties.liu@hotmail.com>
License-Expression: Apache-2.0
Project-URL: Homepage, https://gitee.com/pyboot/commons-jwt
Project-URL: Repository, https://gitee.com/pyboot/commons-jwt
Project-URL: Issues, https://gitee.com/pyboot/commons-jwt
Keywords: web,framework,cli,springboot,fastapi
Classifier: Development Status :: 4 - Beta
Classifier: Intended Audience :: Developers
Classifier: Operating System :: OS Independent
Classifier: Programming Language :: Python :: 3
Classifier: Programming Language :: Python :: 3.8
Classifier: Programming Language :: Python :: 3.9
Classifier: Programming Language :: Python :: 3.10
Classifier: Programming Language :: Python :: 3.11
Classifier: Programming Language :: Python :: 3.12
Classifier: Topic :: Software Development :: Libraries :: Application Frameworks
Requires-Python: >=3.12.10
License-File: LICENSE
Requires-Dist: pyboot-commons-utils
Requires-Dist: pyjwt==2.10.1
Dynamic: license-file
